tap_pagerduty/__init__.py
tap_pagerduty/streams.py
tap_pagerduty/version.py
tap_pagerduty/schemas/escalation_policies.json
tap_pagerduty/schemas/incidents.json
tap_pagerduty/schemas/notifications.json
tap_pagerduty/schemas/services.json
tap_pagerduty-0.1.1.dist-info/LICENSE
tap_pagerduty-0.1.1.dist-info/METADATA
tap_pagerduty-0.1.1.dist-info/WHEEL
tap_pagerduty-0.1.1.dist-info/entry_points.txt
tap_pagerduty-0.1.1.dist-info/top_level.txt
tap_pagerduty-0.1.1.dist-info/RECORD
